{"you": 1, "is": 2, "do": 3, "are": 4, "how": 5, "your": 6, "who": 7, "hi": 8, "what": 9, "the": 10, "a": 11, "good": 12, "in": 13, "which": 14, "to": 15, "age": 16, "where": 17, "hello": 18, "day": 19, "made": 20, "nice": 21, "meet": 22, "of": 23, "have": 24, "does": 25, "exist": 26, "written": 27, "code": 28, "jenni": 29, "boy": 30, "baby": 31, "life": 32, "god": 33, "sleep": 34, "morning": 35, "love": 36, "me": 37, "like": 38, "old": 39, "language": 40, "bot": 41, "chatbot": 42, "weather": 43, "was": 44, "weekend": 45, "whats": 46, "up": 47, "father": 48, "mother": 49, "created": 50, "lord": 51, "rama": 52, "eat": 53, "walk": 54, "greetings": 55, "it": 56, "pleasure": 57, "top": 58, "night": 59, "evening": 60, "know": 61, "joke": 62, "you\u2019re": 63, "funny": 64, "i": 65, "will": 66, "marry": 67, "single": 68, "people": 69, "santa": 70, "claus": 71, "part": 72, "matrix": 73, "cute": 74, "beautiful": 75, "arehandsome": 76, "hobby": 77, "smart": 78, "clever": 79, "intelligent": 80, "ghost": 81, "got": 82, "laugh": 83, "run": 84, "play": 85, "get": 86, "angry": 87, "framework": 88, "api": 89, "speak": 90}